{"Session 0": {"thetalks": [{"speaker": "Bisasam", "start": "2023-03-12T16:34:00", "end": "2023-03-12T16:34:10", "showclock": false, "kind": "regular"}, {"speaker": "Bisaknosp", "start": "2023-03-12T16:34:10", "end": "2023-03-12T16:34:20", "showclock": false, "kind": "regular"}, {"speaker": "Bisaflor", "start": "2023-03-12T16:34:20", "end": "2023-03-12T16:34:30", "showclock": false, "kind": "regular"}, {"speaker": "Glumanda", "start": "2023-03-12T16:34:30", "end": "2023-03-12T16:34:40", "showclock": false, "kind": "regular"}, {"speaker": "COFFEEEE", "start": "2023-03-12T16:34:40", "end": "2023-03-12T16:34:50", "showclock": true, "kind": "pause"}, {"speaker": "Glurak", "start": "2023-03-12T16:34:50", "end": "2023-03-12T16:35:00", "showclock": false, "kind": "regular"}, {"speaker": "Schiggy", "start": "2023-03-12T16:35:00", "end": "2023-03-12T16:35:10", "showclock": false, "kind": "regular"}, {"speaker": "Schillok", "start": "2023-03-12T16:35:10", "end": "2023-03-12T16:35:20", "showclock": false, "kind": "regular"}, {"speaker": "Turtok", "start": "2023-03-12T16:35:20", "end": "2023-03-12T16:35:30", "showclock": false, "kind": "regular"}, {"speaker": "COFFEEEE", "start": "2023-03-12T16:35:30", "end": "2023-03-12T16:35:40", "showclock": true, "kind": "pause"}]}, "Session 1": {"thetalks": [{"speaker": "Safcon", "start": "2023-03-12T16:34:00", "end": "2023-03-12T16:34:10", "showclock": false, "kind": "regular"}, {"speaker": "Smettbo", "start": "2023-03-12T16:34:10", "end": "2023-03-12T16:34:20", "showclock": false, "kind": "regular"}, {"speaker": "Hornliu", "start": "2023-03-12T16:34:20", "end": "2023-03-12T16:34:30", "showclock": false, "kind": "regular"}, {"speaker": "Kokuna", "start": "2023-03-12T16:34:30", "end": "2023-03-12T16:34:40", "showclock": false, "kind": "regular"}, {"speaker": "COFFEEEE", "start": "2023-03-12T16:34:40", "end": "2023-03-12T16:34:50", "showclock": true, "kind": "pause"}, {"speaker": "Taubsi", "start": "2023-03-12T16:34:50", "end": "2023-03-12T16:35:00", "showclock": false, "kind": "regular"}, {"speaker": "Tauboga", "start": "2023-03-12T16:35:00", "end": "2023-03-12T16:35:10", "showclock": false, "kind": "regular"}, {"speaker": "Tauboss", "start": "2023-03-12T16:35:10", "end": "2023-03-12T16:35:20", "showclock": false, "kind": "regular"}, {"speaker": "Rattfratz", "start": "2023-03-12T16:35:20", "end": "2023-03-12T16:35:30", "showclock": false, "kind": "regular"}, {"speaker": "COFFEEEE", "start": "2023-03-12T16:35:30", "end": "2023-03-12T16:35:40", "showclock": true, "kind": "pause"}]}}